rpsa_backend/__init__.py
rpsa_backend/_arena.py
rpsa_backend/arena.py
rpsa_backend/config.py
rpsa_backend/models.py
rpsa_backend/public_api/__init__.py
rpsa_backend/public_api/auth.py
rpsa_backend/public_api/extensions.py
rpsa_backend/public_api/routes/arenas.py
rpsa_backend/public_api/routes/games.py
rpsa_backend/public_api/routes/strategies.py
rpsa_backend/public_api/schemas.py
rpsa_backend/public_api/utils.py
rpsa_backend/random_strategy.py
rpsa_backend/README.md
rpsa_backend/routes/admin.py
rpsa_backend/routes/arena.py
rpsa_backend/routes/data/stats.py
rpsa_backend/routes/strategy.py
rpsa_backend/routes/user.py
rpsa_backend/safety.py
rpsa_backend/utils.py
rpsa_backend/validation.py
rpsa_backend-1.0.3.dist-info/METADATA
rpsa_backend-1.0.3.dist-info/WHEEL
rpsa_backend-1.0.3.dist-info/RECORD
