Metadata-Version: 2.1
Name: rpsa-backend
Version: 1.0.3
Summary: Automatically generated by Nx.
License: Proprietary
Requires-Python: >=3.11,<3.12
Classifier: License :: Other/Proprietary License
Classifier: Programming Language :: Python :: 3
Classifier: Programming Language :: Python :: 3.11
Requires-Dist: azure-storage-blob (>=12.25.1,<13.0.0)
Requires-Dist: flask (>=3.0.3,<4.0.0)
Requires-Dist: flask-caching (>=2.3.1,<3.0.0)
Requires-Dist: flask-cors (>=4.0.1,<5.0.0)
Requires-Dist: flask-executor (>=1.0.0,<2.0.0)
Requires-Dist: flask-limiter (<3.0)
Requires-Dist: flask-migrate (>=4.0.7,<5.0.0)
Requires-Dist: flask-sqlalchemy (>=3.1.1,<4.0.0)
Requires-Dist: marshmallow (>=4.0.0,<5.0.0)
Requires-Dist: marshmallow-sqlalchemy (>=1.4.2,<2.0.0)
Requires-Dist: numpy (>=1.23,<2.0)
Requires-Dist: onnxruntime (>=1.22.0,<2.0.0)
Requires-Dist: poetry-plugin-export (>=1.8.0,<2.0.0)
Requires-Dist: pymssql (>=2.3.2,<3.0.0)
Requires-Dist: pyodbc (>=5.2.0,<6.0.0)
Requires-Dist: rpsa-sdk (==0.1.1)
Requires-Dist: tenacity (>=9.1.2,<10.0.0)
Requires-Dist: torch (==2.0.0+cpu)
Requires-Dist: typing-extensions (>=4.13.2,<5.0.0)
Requires-Dist: waitress (>=3.0.0,<4.0.0)
